ptmanager/__init__.py
ptmanager/_version.py
ptmanager/ptmanager.py
ptmanager/modules/__init__.py
ptmanager/modules/burp_listener.py
ptmanager/modules/config.py
ptmanager/modules/process.py
ptmanager/modules/project_manager.py
ptmanager/modules/tools_manager.py
ptmanager/modules/utils.py
ptmanager/modules/daemon/__init__.py
ptmanager/modules/daemon/daemon.py
ptmanager/modules/daemon/task_store.py
ptmanager/modules/hooks/__init__.py
ptmanager/modules/hooks/ptwordlists.py
ptmanager-0.0.42.dist-info/licenses/LICENSE
ptmanager-0.0.42.dist-info/METADATA
ptmanager-0.0.42.dist-info/WHEEL
ptmanager-0.0.42.dist-info/entry_points.txt
ptmanager-0.0.42.dist-info/top_level.txt
ptmanager-0.0.42.dist-info/RECORD
